camtasia/__init__.py
camtasia/authoring_client.py
camtasia/cli.py
camtasia/color.py
camtasia/effects.py
camtasia/extras.py
camtasia/frame_stamp.py
camtasia/operations.py
camtasia/project.py
camtasia/version.py
camtasia/annotations/__init__.py
camtasia/annotations/callouts.py
camtasia/annotations/shapes.py
camtasia/annotations/types.py
camtasia/media_bin/__init__.py
camtasia/media_bin/media_bin.py
camtasia/resources/new.cmproj/bookmarks.plist
camtasia/resources/new.cmproj/docPrefs
camtasia/resources/new.cmproj/project.tscproj
camtasia/timeline/__init__.py
camtasia/timeline/marker.py
camtasia/timeline/timeline.py
camtasia/timeline/track.py
camtasia/timeline/track_media.py
camtasia-6.3.1.dist-info/LICENSE
camtasia-6.3.1.dist-info/METADATA
camtasia-6.3.1.dist-info/WHEEL
camtasia-6.3.1.dist-info/entry_points.txt
camtasia-6.3.1.dist-info/top_level.txt
camtasia-6.3.1.dist-info/RECORD
