Metadata-Version: 2.1
Name: camtasia
Version: 6.3.1
Summary: Python API for Camtasia projects
Home-page: https://github.com/sixty-north/python-camtasia
Author: Sixty North AS
Author-email: austin@sixty-north.com
License: MIT
Platform: any
Classifier: Development Status :: 3 - Alpha
Classifier: Operating System :: OS Independent
Classifier: Programming Language :: Python
Classifier: Programming Language :: Python :: 3 :: Only
License-File: LICENSE
Requires-Dist: exit-codes (<2.0.0,>=1.3.0)
Requires-Dist: docopt-subcommands
Requires-Dist: pymediainfo
Requires-Dist: marshmallow
Requires-Dist: marshmallow-oneofschema
Provides-Extra: dev
Requires-Dist: bumpversion ; extra == 'dev'
Provides-Extra: test
Requires-Dist: hypothesis ; extra == 'test'
Requires-Dist: pytest ; extra == 'test'
